{
  "total_events": 1042,
  "active_events": 902,
  "total_scrapers": 6,
  "successful_scrapers": 6,
  "failed_scrapers_count": 0,
  "by_store": {
    "Arte 9": {
      "total": 290,
      "active": 277,
      "raw_this_run": 277,
      "previous_raw": 0,
      "dropped_this_run": 0,
      "drop_reasons": {
        "missing_fields": 0,
        "bad_datetime": 0
      },
      "scraper_failed": false,
      "anomaly": null
    },
    "Ítaca": {
      "total": 237,
      "active": 156,
      "raw_this_run": 156,
      "previous_raw": 75,
      "dropped_this_run": 0,
      "drop_reasons": {
        "missing_fields": 0,
        "bad_datetime": 0
      },
      "scraper_failed": false,
      "anomaly": null
    },
    "Jupiter Juegos": {
      "total": 201,
      "active": 195,
      "raw_this_run": 195,
      "previous_raw": 143,
      "dropped_this_run": 0,
      "drop_reasons": {
        "missing_fields": 0,
        "bad_datetime": 0
      },
      "scraper_failed": false,
      "anomaly": null
    },
    "Micelion Games": {
      "total": 168,
      "active": 138,
      "raw_this_run": 138,
      "previous_raw": 138,
      "dropped_this_run": 0,
      "drop_reasons": {
        "missing_fields": 0,
        "bad_datetime": 0
      },
      "scraper_failed": false,
      "anomaly": null
    },
    "La Guarida Juegos": {
      "total": 88,
      "active": 88,
      "raw_this_run": 88,
      "previous_raw": 72,
      "dropped_this_run": 0,
      "drop_reasons": {
        "missing_fields": 0,
        "bad_datetime": 0
      },
      "scraper_failed": false,
      "anomaly": null
    },
    "Metropolis Center": {
      "total": 58,
      "active": 48,
      "raw_this_run": 48,
      "previous_raw": 50,
      "dropped_this_run": 0,
      "drop_reasons": {
        "missing_fields": 0,
        "bad_datetime": 0
      },
      "scraper_failed": false,
      "anomaly": null
    }
  },
  "by_game": {
    "Magic: The Gathering": 452,
    "Riftbound": 198,
    "Unknown": 109,
    "Lorcana": 83,
    "One Piece": 70,
    "Flesh and Blood": 32,
    "Star Wars: Unlimited": 21,
    "Pokémon": 21,
    "Digimon": 21,
    "Final Fantasy TCG": 13,
    "Weiß Schwarz": 10,
    "Yu-Gi-Oh!": 6,
    "Naruto Mythos": 6
  },
  "scrapers": {
    "scrapers.arte9": {
      "store": "Arte 9",
      "raw": 277,
      "valid": 277,
      "dropped": 0,
      "drop_reasons": {
        "missing_fields": 0,
        "bad_datetime": 0
      },
      "error": null,
      "previous_raw": 0,
      "anomaly": null
    },
    "scrapers.itaca": {
      "store": "Ítaca",
      "raw": 156,
      "valid": 156,
      "dropped": 0,
      "drop_reasons": {
        "missing_fields": 0,
        "bad_datetime": 0
      },
      "error": null,
      "previous_raw": 75,
      "anomaly": null
    },
    "scrapers.jupiter_juegos": {
      "store": "Jupiter Juegos",
      "raw": 195,
      "valid": 195,
      "dropped": 0,
      "drop_reasons": {
        "missing_fields": 0,
        "bad_datetime": 0
      },
      "error": null,
      "previous_raw": 143,
      "anomaly": null
    },
    "scrapers.la_guarida_juegos": {
      "store": "La Guarida Juegos",
      "raw": 88,
      "valid": 88,
      "dropped": 0,
      "drop_reasons": {
        "missing_fields": 0,
        "bad_datetime": 0
      },
      "error": null,
      "previous_raw": 72,
      "anomaly": null
    },
    "scrapers.metropolis_center": {
      "store": "Metropolis Center",
      "raw": 48,
      "valid": 48,
      "dropped": 0,
      "drop_reasons": {
        "missing_fields": 0,
        "bad_datetime": 0
      },
      "error": null,
      "previous_raw": 50,
      "anomaly": null
    },
    "scrapers.micelion_games": {
      "store": "Micelion Games",
      "raw": 138,
      "valid": 138,
      "dropped": 0,
      "drop_reasons": {
        "missing_fields": 0,
        "bad_datetime": 0
      },
      "error": null,
      "previous_raw": 138,
      "anomaly": null
    }
  },
  "failed_scrapers": [],
  "generated_at": "2026-05-01T10:20:23.787065+02:00"
}